selfmemory/__init__.py
selfmemory/_version.py
selfmemory/cli.py
selfmemory/exceptions.py
selfmemory/client/__init__.py
selfmemory/client/main.py
selfmemory/client/project.py
selfmemory/client/utils.py
selfmemory/common/__init__.py
selfmemory/common/constants.py
selfmemory/configs/__init__.py
selfmemory/configs/base.py
selfmemory/configs/enums.py
selfmemory/configs/prompts.py
selfmemory/configs/embeddings/__init__.py
selfmemory/configs/embeddings/base.py
selfmemory/configs/llms/anthropic.py
selfmemory/configs/llms/aws_bedrock.py
selfmemory/configs/llms/azure.py
selfmemory/configs/llms/base.py
selfmemory/configs/llms/deepseek.py
selfmemory/configs/llms/lmstudio.py
selfmemory/configs/llms/ollama.py
selfmemory/configs/llms/openai.py
selfmemory/configs/llms/vllm.py
selfmemory/configs/vector_stores/__init__.py
selfmemory/configs/vector_stores/azure_ai_search.py
selfmemory/configs/vector_stores/baidu.py
selfmemory/configs/vector_stores/chroma.py
selfmemory/configs/vector_stores/databricks.py
selfmemory/configs/vector_stores/elasticsearch.py
selfmemory/configs/vector_stores/faiss.py
selfmemory/configs/vector_stores/langchain.py
selfmemory/configs/vector_stores/milvus.py
selfmemory/configs/vector_stores/mongodb.py
selfmemory/configs/vector_stores/neptune.py
selfmemory/configs/vector_stores/opensearch.py
selfmemory/configs/vector_stores/pgvector.py
selfmemory/configs/vector_stores/pinecone.py
selfmemory/configs/vector_stores/qdrant.py
selfmemory/configs/vector_stores/redis.py
selfmemory/configs/vector_stores/s3_vectors.py
selfmemory/configs/vector_stores/supabase.py
selfmemory/configs/vector_stores/upstash_vector.py
selfmemory/configs/vector_stores/valkey.py
selfmemory/configs/vector_stores/vertex_ai_vector_search.py
selfmemory/configs/vector_stores/weaviate.py
selfmemory/embeddings/__init__.py
selfmemory/embeddings/aws_bedrock.py
selfmemory/embeddings/azure_openai.py
selfmemory/embeddings/base.py
selfmemory/embeddings/configs.py
selfmemory/embeddings/gemini.py
selfmemory-0.5.2.dist-info/licenses/LICENSE.txt
selfmemory-0.5.2.dist-info/METADATA
selfmemory-0.5.2.dist-info/WHEEL
selfmemory-0.5.2.dist-info/entry_points.txt
selfmemory-0.5.2.dist-info/top_level.txt
selfmemory-0.5.2.dist-info/RECORD
