Metadata-Version: 2.4
Name: selfmemory
Version: 0.5.2
Summary: Enhanced Memory Management for AI Agents with zero-setup simplicity
Author: SelfMemory Team
Maintainer: SelfMemory Team
License-Expression: Apache-2.0
Project-URL: Homepage, https://selfmemory.com
Project-URL: Repository, https://github.com/selfmemory/selfmemory
Project-URL: Documentation, https://github.com/selfmemory/selfmemory/wiki
Project-URL: Issues, https://github.com/selfmemory/selfmemory/issues
Project-URL: Changelog, https://github.com/selfmemory/selfmemory/blob/main/CHANGELOG.md
Keywords: memory,ai,ml,vector,search,embeddings,agents,llm,artificial-intelligence,qdrant,semantic-search
Classifier: Development Status :: 4 - Beta
Classifier: Intended Audience :: Developers
Classifier: Operating System :: OS Independent
Classifier: Programming Language :: Python :: 3
Classifier: Programming Language :: Python :: 3.10
Classifier: Programming Language :: Python :: 3.11
Classifier: Programming Language :: Python :: 3.12
Classifier: Programming Language :: Python :: 3.13
Classifier: Topic :: Scientific/Engineering :: Artificial Intelligence
Classifier: Topic :: Software Development :: Libraries :: Python Modules
Classifier: Topic :: Database :: Database Engines/Servers
Classifier: Topic :: Text Processing :: Indexing
Classifier: Typing :: Typed
Requires-Python: >=3.10
License-File: LICENSE.txt
Requires-Dist: chromadb>=0.4.0
Requires-Dist: qdrant-client>=1.6.0
Requires-Dist: pydantic<3.0.0,>=2.0.0
Requires-Dist: email-validator>=2.0.0
Requires-Dist: python-dotenv>=1.0.0
Requires-Dist: cryptography>=40.0.0
Requires-Dist: httpx>=0.25.0
Requires-Dist: pyyaml>=6.0.0
Provides-Extra: test
Requires-Dist: pytest>=7.0.0; extra == "test"
Requires-Dist: pytest-asyncio>=0.21.0; extra == "test"
Requires-Dist: pytest-mock>=3.10.0; extra == "test"
Requires-Dist: pytest-cov>=4.0.0; extra == "test"
Requires-Dist: responses>=0.23.0; extra == "test"
Provides-Extra: dev
Requires-Dist: pytest>=7.0.0; extra == "dev"
Requires-Dist: pytest-asyncio>=0.21.0; extra == "dev"
Requires-Dist: pytest-mock>=3.10.0; extra == "dev"
Requires-Dist: pytest-cov>=4.0.0; extra == "dev"
Requires-Dist: responses>=0.23.0; extra == "dev"
Requires-Dist: ruff>=0.14.8; extra == "dev"
Requires-Dist: pre-commit>=4.3.0; extra == "dev"
Requires-Dist: build>=1.3.0; extra == "dev"
Requires-Dist: twine>=6.1.0; extra == "dev"
Requires-Dist: python-semantic-release>=9.0.0; extra == "dev"
Requires-Dist: fastapi>=0.100.0; extra == "dev"
Requires-Dist: fastapi-csrf-protect>=0.3.0; extra == "dev"
Requires-Dist: uvicorn>=0.20.0; extra == "dev"
Requires-Dist: starlette>=0.27.0; extra == "dev"
Requires-Dist: psutil>=5.9.0; extra == "dev"
Requires-Dist: pymongo>=4.0.0; extra == "dev"
Requires-Dist: ory-hydra-client>=2.0.0; extra == "dev"
Requires-Dist: ory-kratos-client>=1.0.0; extra == "dev"
Requires-Dist: argon2-cffi>=23.1.0; extra == "dev"
Requires-Dist: authlib>=1.2.0; extra == "dev"
Requires-Dist: google-auth>=2.15.0; extra == "dev"
Requires-Dist: mcp[cli]>=1.13.0; extra == "dev"
Requires-Dist: fastmcp>=2.0.0; extra == "dev"
Requires-Dist: ollama>=0.1.0; extra == "dev"
Requires-Dist: openai>=1.0.0; extra == "dev"
Requires-Dist: opentelemetry-api>=1.20.0; extra == "dev"
Requires-Dist: opentelemetry-sdk>=1.20.0; extra == "dev"
Requires-Dist: opentelemetry-exporter-otlp>=1.20.0; extra == "dev"
Requires-Dist: opentelemetry-instrumentation-fastapi>=0.41b0; extra == "dev"
Requires-Dist: opentelemetry-instrumentation-httpx>=0.41b0; extra == "dev"
Requires-Dist: opentelemetry-instrumentation-pymongo>=0.41b0; extra == "dev"
Requires-Dist: opentelemetry-instrumentation-logging>=0.41b0; extra == "dev"
Dynamic: license-file
